{
    "food1": {
        "x": 0,
        "y": 96,
        "width": 76,
        "height": 76,
        "source_image": "images/food/food1.png",
        "image": "../images/foods.png",
        "total_width": 76,
        "total_height": 1324,
        "offset_x": 0,
        "offset_y": -96,
        "px": {
            "x": "0px",
            "y": "96px",
            "offset_x": "0px",
            "offset_y": "-96px",
            "height": "76px",
            "width": "76px",
            "total_height": "1324px",
            "total_width": "76px"
        },
        "escaped_image": "../images/foods.png"
    },
    "food10": {
        "x": 0,
        "y": 672,
        "width": 76,
        "height": 76,
        "source_image": "images/food/food10.png",
        "image": "../images/foods.png",
        "total_width": 76,
        "total_height": 1324,
        "offset_x": 0,
        "offset_y": -672,
        "px": {
            "x": "0px",
            "y": "672px",
            "offset_x": "0px",
            "offset_y": "-672px",
            "height": "76px",
            "width": "76px",
            "total_height": "1324px",
            "total_width": "76px"
        },
        "escaped_image": "../images/foods.png"
    },
    "food11": {
        "x": 0,
        "y": 192,
        "width": 76,
        "height": 76,
        "source_image": "images/food/food11.png",
        "image": "../images/foods.png",
        "total_width": 76,
        "total_height": 1324,
        "offset_x": 0,
        "offset_y": -192,
        "px": {
            "x": "0px",
            "y": "192px",
            "offset_x": "0px",
            "offset_y": "-192px",
            "height": "76px",
            "width": "76px",
            "total_height": "1324px",
            "total_width": "76px"
        },
        "escaped_image": "../images/foods.png"
    },
    "food12": {
        "x": 0,
        "y": 288,
        "width": 76,
        "height": 76,
        "source_image": "images/food/food12.png",
        "image": "../images/foods.png",
        "total_width": 76,
        "total_height": 1324,
        "offset_x": 0,
        "offset_y": -288,
        "px": {
            "x": "0px",
            "y": "288px",
            "offset_x": "0px",
            "offset_y": "-288px",
            "height": "76px",
            "width": "76px",
            "total_height": "1324px",
            "total_width": "76px"
        },
        "escaped_image": "../images/foods.png"
    },
    "food13": {
        "x": 0,
        "y": 384,
        "width": 76,
        "height": 76,
        "source_image": "images/food/food13.png",
        "image": "../images/foods.png",
        "total_width": 76,
        "total_height": 1324,
        "offset_x": 0,
        "offset_y": -384,
        "px": {
            "x": "0px",
            "y": "384px",
            "offset_x": "0px",
            "offset_y": "-384px",
            "height": "76px",
            "width": "76px",
            "total_height": "1324px",
            "total_width": "76px"
        },
        "escaped_image": "../images/foods.png"
    },
    "food14": {
        "x": 0,
        "y": 480,
        "width": 76,
        "height": 76,
        "source_image": "images/food/food14.png",
        "image": "../images/foods.png",
        "total_width": 76,
        "total_height": 1324,
        "offset_x": 0,
        "offset_y": -480,
        "px": {
            "x": "0px",
            "y": "480px",
            "offset_x": "0px",
            "offset_y": "-480px",
            "height": "76px",
            "width": "76px",
            "total_height": "1324px",
            "total_width": "76px"
        },
        "escaped_image": "../images/foods.png"
    },
    "food2": {
        "x": 0,
        "y": 576,
        "width": 76,
        "height": 76,
        "source_image": "images/food/food2.png",
        "image": "../images/foods.png",
        "total_width": 76,
        "total_height": 1324,
        "offset_x": 0,
        "offset_y": -576,
        "px": {
            "x": "0px",
            "y": "576px",
            "offset_x": "0px",
            "offset_y": "-576px",
            "height": "76px",
            "width": "76px",
            "total_height": "1324px",
            "total_width": "76px"
        },
        "escaped_image": "../images/foods.png"
    },
    "food3": {
        "x": 0,
        "y": 0,
        "width": 76,
        "height": 76,
        "source_image": "images/food/food3.png",
        "image": "../images/foods.png",
        "total_width": 76,
        "total_height": 1324,
        "offset_x": 0,
        "offset_y": 0,
        "px": {
            "x": "0px",
            "y": "0px",
            "offset_x": "0px",
            "offset_y": "0px",
            "height": "76px",
            "width": "76px",
            "total_height": "1324px",
            "total_width": "76px"
        },
        "escaped_image": "../images/foods.png"
    },
    "food4": {
        "x": 0,
        "y": 768,
        "width": 76,
        "height": 76,
        "source_image": "images/food/food4.png",
        "image": "../images/foods.png",
        "total_width": 76,
        "total_height": 1324,
        "offset_x": 0,
        "offset_y": -768,
        "px": {
            "x": "0px",
            "y": "768px",
            "offset_x": "0px",
            "offset_y": "-768px",
            "height": "76px",
            "width": "76px",
            "total_height": "1324px",
            "total_width": "76px"
        },
        "escaped_image": "../images/foods.png"
    },
    "food5": {
        "x": 0,
        "y": 864,
        "width": 76,
        "height": 76,
        "source_image": "images/food/food5.png",
        "image": "../images/foods.png",
        "total_width": 76,
        "total_height": 1324,
        "offset_x": 0,
        "offset_y": -864,
        "px": {
            "x": "0px",
            "y": "864px",
            "offset_x": "0px",
            "offset_y": "-864px",
            "height": "76px",
            "width": "76px",
            "total_height": "1324px",
            "total_width": "76px"
        },
        "escaped_image": "../images/foods.png"
    },
    "food6": {
        "x": 0,
        "y": 960,
        "width": 76,
        "height": 76,
        "source_image": "images/food/food6.png",
        "image": "../images/foods.png",
        "total_width": 76,
        "total_height": 1324,
        "offset_x": 0,
        "offset_y": -960,
        "px": {
            "x": "0px",
            "y": "960px",
            "offset_x": "0px",
            "offset_y": "-960px",
            "height": "76px",
            "width": "76px",
            "total_height": "1324px",
            "total_width": "76px"
        },
        "escaped_image": "../images/foods.png"
    },
    "food7": {
        "x": 0,
        "y": 1056,
        "width": 76,
        "height": 76,
        "source_image": "images/food/food7.png",
        "image": "../images/foods.png",
        "total_width": 76,
        "total_height": 1324,
        "offset_x": 0,
        "offset_y": -1056,
        "px": {
            "x": "0px",
            "y": "1056px",
            "offset_x": "0px",
            "offset_y": "-1056px",
            "height": "76px",
            "width": "76px",
            "total_height": "1324px",
            "total_width": "76px"
        },
        "escaped_image": "../images/foods.png"
    },
    "food8": {
        "x": 0,
        "y": 1152,
        "width": 76,
        "height": 76,
        "source_image": "images/food/food8.png",
        "image": "../images/foods.png",
        "total_width": 76,
        "total_height": 1324,
        "offset_x": 0,
        "offset_y": -1152,
        "px": {
            "x": "0px",
            "y": "1152px",
            "offset_x": "0px",
            "offset_y": "-1152px",
            "height": "76px",
            "width": "76px",
            "total_height": "1324px",
            "total_width": "76px"
        },
        "escaped_image": "../images/foods.png"
    },
    "food9": {
        "x": 0,
        "y": 1248,
        "width": 76,
        "height": 76,
        "source_image": "images/food/food9.png",
        "image": "../images/foods.png",
        "total_width": 76,
        "total_height": 1324,
        "offset_x": 0,
        "offset_y": -1248,
        "px": {
            "x": "0px",
            "y": "1248px",
            "offset_x": "0px",
            "offset_y": "-1248px",
            "height": "76px",
            "width": "76px",
            "total_height": "1324px",
            "total_width": "76px"
        },
        "escaped_image": "../images/foods.png"
    }
}